MANIFEST.in
README.rst
setup.py
daauto/__init__.py
daauto/text.py
daauto.egg-info/PKG-INFO
daauto.egg-info/SOURCES.txt
daauto.egg-info/dependency_links.txt
daauto.egg-info/not-zip-safe
daauto.egg-info/requires.txt
daauto.egg-info/top_level.txt